datasette_spotify_embed/__init__.py
datasette_spotify_embed/static/datasette-spotify-embed.css
datasette_spotify_embed-0.1.3.dist-info/LICENSE
datasette_spotify_embed-0.1.3.dist-info/METADATA
datasette_spotify_embed-0.1.3.dist-info/WHEEL
datasette_spotify_embed-0.1.3.dist-info/entry_points.txt
datasette_spotify_embed-0.1.3.dist-info/top_level.txt
datasette_spotify_embed-0.1.3.dist-info/RECORD
