Metadata-Version: 2.1
Name: datasette-spotify-embed
Version: 0.1.3
Summary: Turn Spotify track links into iframe embeds in the Datasette interface
Home-page: https://github.com/chekos/datasette-spotify-embed
Author: =?utf-8?q?Sergio_S=C3=A1nchez_Zavala?=
License: Apache License, Version 2.0
Project-URL: Issues, https://github.com/chekos/datasette-spotify-embed/issues
Project-URL: CI, https://github.com/chekos/datasette-spotify-embed/actions
Project-URL: Changelog, https://github.com/chekos/datasette-spotify-embed/releases
Classifier: Framework :: Datasette
Classifier: License :: OSI Approved :: Apache Software License
Requires-Python: >=3.7
License-File: LICENSE
Requires-Dist: datasette
Provides-Extra: test
Requires-Dist: pytest ; extra == 'test'
Requires-Dist: pytest-asyncio ; extra == 'test'
Requires-Dist: sqlite-utils ; extra == 'test'
